[{"name":"sql.active_record","payload":{"sql":"SELECT \"tests\".* FROM \"tests\"","name":"Test Load","connection_id":46923479985220,"statement_name":null,"binds":[],"line":13,"filename":"/learn_react_on_rails/app/views/tests/index.html.erb","method":"_app_views_tests_index_html_erb___3212902546770810198_70017909125740"},"time":"2016-08-20T07:46:39.556+00:00","transaction_id":"39809a1da6ef74c72c66","end":"2016-08-20T07:46:39.558+00:00","children":[],"duration":1.998171},{"name":"render_template.action_view","payload":{"identifier":"/learn_react_on_rails/app/views/tests/index.html.erb","layout":"layouts/application"},"time":"2016-08-20T07:46:39.554+00:00","transaction_id":"2225514a5b5f4609d16d","end":"2016-08-20T07:46:39.559+00:00","children":[],"duration":4.789087},{"name":"process_action.action_controller","payload":{"controller":"TestsController","action":"index","params":{"controller":"tests","action":"index"},"headers":"Not JSON Encodable","format":"html","method":"GET","path":"/tests","status":200,"view_runtime":467.9541129993455,"db_runtime":0.45065500000000003},"time":"2016-08-20T07:46:39.452+00:00","transaction_id":"2225514a5b5f4609d16d","end":"2016-08-20T07:46:39.947+00:00","children":[],"duration":495.289836}]